odoo/addons/web_company_color/README.rst
odoo/addons/web_company_color/__init__.py
odoo/addons/web_company_color/__manifest__.py
odoo/addons/web_company_color/hooks.py
odoo/addons/web_company_color/utils.py
odoo/addons/web_company_color/i18n/ca.po
odoo/addons/web_company_color/i18n/de.po
odoo/addons/web_company_color/i18n/es.po
odoo/addons/web_company_color/i18n/es_AR.po
odoo/addons/web_company_color/i18n/fr.po
odoo/addons/web_company_color/i18n/hr.po
odoo/addons/web_company_color/i18n/it.po
odoo/addons/web_company_color/i18n/nl.po
odoo/addons/web_company_color/i18n/web_company_color.pot
odoo/addons/web_company_color/i18n/zh_CN.po
odoo/addons/web_company_color/models/__init__.py
odoo/addons/web_company_color/models/assetsbundle.py
odoo/addons/web_company_color/models/ir_qweb.py
odoo/addons/web_company_color/models/res_company.py
odoo/addons/web_company_color/readme/CONTRIBUTORS.rst
odoo/addons/web_company_color/readme/DESCRIPTION.rst
odoo/addons/web_company_color/readme/ROADMAP.rst
odoo/addons/web_company_color/readme/USAGE.rst
odoo/addons/web_company_color/static/description/icon.png
odoo/addons/web_company_color/static/description/index.html
odoo/addons/web_company_color/tests/__init__.py
odoo/addons/web_company_color/tests/test_res_company.py
odoo/addons/web_company_color/view/assets.xml
odoo/addons/web_company_color/view/res_company.xml
odoo14_addon_web_company_color-14.0.2.0.0.dist-info/METADATA
odoo14_addon_web_company_color-14.0.2.0.0.dist-info/WHEEL
odoo14_addon_web_company_color-14.0.2.0.0.dist-info/top_level.txt
odoo14_addon_web_company_color-14.0.2.0.0.dist-info/RECORD
